{"school_id": "2514", "data_code": "372014100", "name": "\u9752\u5c9b\u5de5\u5b66\u9662", "type": "5012", "school_type": "6000", "school_nature": "36001", "level": "2001", "code_enroll": "1399500", "belong": "\u5c71\u4e1c\u7701\u6559\u80b2\u5385", "f985": "2", "f211": "2", "department": "2", "admissions": "2", "central": "2", "dual_class": "38003", "is_seal": "1", "num_subject": "0", "num_master": "0", "num_doctor": "0", "num_academician": "0", "num_library": "88\u4e07", "num_lab": "0", "province_id": "37", "city_id": "3702", "county_id": "0", "is_ads": "2", "is_recruitment": "1", "create_date": "2005", "area": 1046, "old_name": "\u4e2d\u56fd\u6d77\u6d0b\u5927\u5b66\u9752\u5c9b\u5b66\u9662", "status": "1", "add_id": "0", "add_time": "2018-12-08 17:23:24", "update_id": "0", "update_time": "2021-03-18 11:11:11", "ad_level": "2", "short": "\u9752\u5de5\u9662", "e_pc": "1", "e_app": "1", "ruanke_rank": "0", "single": "75001,75008", "colleges_level": "", "doublehigh": "0", "wsl_rank": "0", "qs_rank": "0", "xyh_rank": "0", "is_sell": "1", "eol_rank": "880", "school_batch": "8,9,10,14,17,158,18,1565,1570,1571", "us_rank": "0", "is_logo": "1", "num_master2": "0", "num_doctor2": "0", "ai_status": "1", "logo": "/app/html/upload/logo/2514.jpg", "level_name": "\u666e\u901a\u672c\u79d1", "type_name": "\u5176\u4ed6", "school_type_name": "\u666e\u901a\u672c\u79d1", "school_nature_name": "\u6c11\u529e", "dual_class_name": "", "xueke_rank": {}, "single_province": "37,37", "remark": [], "province_name": "\u5c71\u4e1c", "city_name": "\u9752\u5c9b\u5e02", "town_name": "", "weiwangzhan": "", "urllinks": {"71009": {"school_id": "2514", "link": "http://www.oucqdc.edu.cn/", "type": "71009", "img_url": "", "title": ""}, "71008": {"school_id": "2514", "link": "http://www.oucqdc.edu.cn/", "type": "71008", "img_url": "", "title": ""}, "71007": {"school_id": "2514", "link": "http://www.sdzk.cn/", "type": "71007", "img_url": "", "title": ""}, "71005": {"school_id": "2514", "link": "https://m-view.eol.cn/h5/zsgk/answer_noresult.html?t=1111", "type": "71005", "img_url": "", "title": ""}, "71006": {"school_id": "2514", "link": "https://s11.cnzz.com/z_stat.php?id=1258540390&web_id=1258540390", "type": "71006", "img_url": "", "title": ""}}, "yjszs": "", "xiaoyuan": "", "email": "qdgxyzsb@163.com", "school_email": "", "address": "\u5c71\u4e1c\u7701\u9752\u5c9b\u80f6\u5dde\u5e02\u798f\u5dde\u5357\u8def236\u53f7", "postcode": "266300", "site": "", "school_site": "http://www.qit.edu.cn/", "phone": "0532-82285001,0532-82285000", "school_phone": "", "content": "\u4e00\u3001\u529e\u5b66\u5386\u7a0b\u9752\u5c9b\u5de5\u5b66\u9662\u524d\u8eab\u4e3a2005\u5e74\u5efa\u6821\u7684\u4e2d\u56fd\u6d77\u6d0b\u5927\u5b66\u9752\u5c9b\u5b66\u9662\uff0c\u662f\u7531\u4e2d\u56fd\u6d77\u6d0b\u5927\u5b66\u7533\u529e\u3001\u65b0\u7586\u751f\u4ea7\u5efa\u8bbe\u5175\u56e2\u4e0b\u5c5e\u7684\u9752\u5c9b\u4f0a\u529b\u7279\u5fb7\u6cf0\u79d1\u6559\u6295\u8d44\u7ba1\u7406\u6709\u9650\u516c\u53f8\u6295\u8d44\u4e3e\u529e\u7684\u72ec\u7acb\u5b66\u9662\u3002\u7ecf\u6559\u80b2\u90e8\u6279\u51c6\uff0c\u5b66\u6821\u4e8e2011\u5e74\u8f6c\u8bbe\u4e3a\u72ec\u7acb\u5efa\u5236\u7684\u6c11\u529e\u666e\u901a\u672c\u79d1\u9ad8\u6821\uff0c\u66f4\u540d\u4e3a\u9752\u5c9b\u5de5\u5b66\u9662\u3002\u4e8c\u3001\u529e\u5b66\u5b9a\u4f4d\u5b66\u6821\u529e\u5b66\u5c42\u6b21\u4e3a\u672c\u79d1\u9ad8\u6821\uff0c\u540c\u65f6\u4e3e\u529e\u4e13\u79d1\u6559\u80b2;\u529e\u5b66\u6027\u8d28\u53ca\u7c7b\u578b\u4e3a\u5168\u65e5\u5236\u666e\u901a\u6c11\u529e\u672c\u79d1\u9ad8\u7b49\u5b66\u6821;\u4eba", "video": {}, "video_pc": {"school_id": "2514", "url": "", "url_type": "1", "img_url": "https://static-data.eol.cn//upload/svideo/1611711814_3393_thumb.png"}, "is_video": 1, "dualclass": [], "special": [{"id": "81226", "school_id": "2514", "special_id": "172", "nation_feature": "2", "province_feature": "2", "is_important": "1", "limit_year": "\u56db\u5e74", "year": "2019", "level3_weight": "0", "is_video": 2, "special_name": "\u8ba1\u7b97\u673a\u79d1\u5b66\u4e0e\u6280\u672f", "level_name": "\u672c\u79d1"}, {"id": "81230", "school_id": "2514", "special_id": "167", "nation_feature": "2", "province_feature": "2", "is_important": "1", "limit_year": "\u56db\u5e74", "year": "2019", "level3_weight": "0", "is_video": 2, "special_name": "\u901a\u4fe1\u5de5\u7a0b", "level_name": "\u672c\u79d1"}, {"id": "81245", "school_id": "2514", "special_id": "236", "nation_feature": "2", "province_feature": "2", "is_important": "1", "limit_year": "\u56db\u5e74", "year": "2019", "level3_weight": "0", "is_video": 2, "special_name": "\u98df\u54c1\u79d1\u5b66\u4e0e\u5de5\u7a0b", "level_name": "\u672c\u79d1"}, {"id": "81254", "school_id": "2514", "special_id": "301", "nation_feature": "2", "province_feature": "2", "is_important": "1", "limit_year": "\u56db\u5e74", "year": "2019", "level3_weight": "0", "is_video": 2, "special_name": "\u56fd\u9645\u5546\u52a1", "level_name": "\u672c\u79d1"}, {"id": "81255", "school_id": "2514", "special_id": "163", "nation_feature": "2", "province_feature": "2", "is_important": "1", "limit_year": "\u56db\u5e74", "year": "2019", "level3_weight": "0", "is_video": 2, "special_name": "\u80fd\u6e90\u4e0e\u52a8\u529b\u5de5\u7a0b", "level_name": "\u672c\u79d1"}, {"id": "81250", "school_id": "2514", "special_id": "47", "nation_feature": "2", "province_feature": "2", "is_important": "2", "limit_year": "\u56db\u5e74", "year": "2019", "level3_weight": "0", "is_video": 2, "special_name": "\u5fb7\u8bed", "level_name": "\u672c\u79d1"}, {"id": "81249", "school_id": "2514", "special_id": "783", "nation_feature": "2", "province_feature": "2", "is_important": "2", "limit_year": "\u4e09\u5e74", "year": "2019", "level3_weight": "0", "is_video": 2, "special_name": "\u8ba1\u7b97\u673a\u5e94\u7528\u6280\u672f", "level_name": "\u4e13\u79d1"}, {"id": "81222", "school_id": "2514", "special_id": "51", "nation_feature": "2", "province_feature": "2", "is_important": "2", "limit_year": "\u56db\u5e74", "year": "2019", "level3_weight": "0", "is_video": 2, "special_name": "\u65e5\u8bed", "level_name": "\u672c\u79d1"}, {"id": "81224", "school_id": "2514", "special_id": "53", "nation_feature": "2", "province_feature": "2", "is_important": "2", "limit_year": "\u56db\u5e74", "year": "2019", "level3_weight": "0", "is_video": 2, "special_name": "\u671d\u9c9c\u8bed", "level_name": "\u672c\u79d1"}, {"id": "81227", "school_id": "2514", "special_id": "165", "nation_feature": "2", "province_feature": "2", "is_important": "2", "limit_year": "\u56db\u5e74", "year": "2019", "level3_weight": "0", "is_video": 2, "special_name": "\u7535\u5b50\u4fe1\u606f\u5de5\u7a0b", "level_name": "\u672c\u79d1"}], "nature_name": "\u6c11\u529e", "province_score_min": {"12": {"school_id": "2514", "province_id": "12", "type": "3", "min": "476.00", "year": "2020"}, "13": {"school_id": "2514", "province_id": "13", "type": "2", "min": "486.00", "year": "2020"}, "14": {"school_id": "2514", "province_id": "14", "type": "2", "min": "414.00", "year": "2020"}, "15": {"school_id": "2514", "province_id": "15", "type": "2", "min": "438.00", "year": "2020"}, "21": {"school_id": "2514", "province_id": "21", "type": "2", "min": "507.00", "year": "2020"}, "22": {"school_id": "2514", "province_id": "22", "type": "2", "min": "417.00", "year": "2020"}, "23": {"school_id": "2514", "province_id": "23", "type": "2", "min": "401.00", "year": "2020"}, "32": {"school_id": "2514", "province_id": "32", "type": "1", "min": "320.00", "year": "2020"}, "33": {"school_id": "2514", "province_id": "33", "type": "3", "min": "495.00", "year": "2020"}, "34": {"school_id": "2514", "province_id": "34", "type": "2", "min": "505.00", "year": "2020"}, "35": {"school_id": "2514", "province_id": "35", "type": "1", "min": "402.00", "year": "2020"}, "36": {"school_id": "2514", "province_id": "36", "type": "2", "min": "498.00", "year": "2020"}, "37": {"school_id": "2514", "province_id": "37", "type": "3", "min": "456.00", "year": "2020"}, "41": {"school_id": "2514", "province_id": "41", "type": "2", "min": "470.00", "year": "2020"}, "42": {"school_id": "2514", "province_id": "42", "type": "2", "min": "429.00", "year": "2020"}, "43": {"school_id": "2514", "province_id": "43", "type": "2", "min": "526.00", "year": "2020"}, "44": {"school_id": "2514", "province_id": "44", "type": "2", "min": "461.00", "year": "2020"}, "45": {"school_id": "2514", "province_id": "45", "type": "1", "min": "363.00", "year": "2020"}, "46": {"school_id": "2514", "province_id": "46", "type": "3", "min": "481.00", "year": "2020"}, "50": {"school_id": "2514", "province_id": "50", "type": "2", "min": "514.00", "year": "2020"}, "51": {"school_id": "2514", "province_id": "51", "type": "2", "min": "462.00", "year": "2020"}, "52": {"school_id": "2514", "province_id": "52", "type": "2", "min": "465.00", "year": "2020"}, "53": {"school_id": "2514", "province_id": "53", "type": "2", "min": "481.00", "year": "2020"}, "61": {"school_id": "2514", "province_id": "61", "type": "2", "min": "429.00", "year": "2020"}, "62": {"school_id": "2514", "province_id": "62", "type": "2", "min": "443.00", "year": "2020"}, "63": {"school_id": "2514", "province_id": "63", "type": "2", "min": "412.00", "year": "2020"}, "64": {"school_id": "2514", "province_id": "64", "type": "2", "min": "473.00", "year": "2020"}, "65": {"school_id": "2514", "province_id": "65", "type": "2", "min": "372.00", "year": "2020"}}, "pro_type_min": {"12": [{"year": 2020, "type": {"3": "476.00"}}, {"year": 2019, "type": {"2": "422.00", "1": "394.00"}}, {"year": 2018, "type": {"2": "407.00", "1": "391.00"}}], "13": [{"year": 2020, "type": {"2": "486.00", "1": "463.00"}}, {"year": 2019, "type": {"2": "486.00", "1": "432.00"}}, {"year": 2018, "type": {"2": "468.00", "1": "413.00"}}], "14": [{"year": 2020, "type": {"2": "414.00", "1": "378.00"}}, {"year": 2019, "type": {"2": "416.00", "1": "358.00"}}, {"year": 2018, "type": {"2": "394.00", "1": "342.00"}}], "15": [{"year": 2020, "type": {"2": "438.00", "1": "334.00"}}, {"year": 2019, "type": {"2": "437.00", "1": "345.00"}}, {"year": 2018, "type": {"2": "399.00", "1": "336.00"}}], "21": [{"year": 2020, "type": {"2": "507.00", "1": "425.00"}}, {"year": 2019, "type": {"2": "504.00", "1": "426.00"}}, {"year": 2018, "type": {"2": "473.00", "1": "417.00"}}], "22": [{"year": 2020, "type": {"2": "417.00", "1": "360.00"}}, {"year": 2019, "type": {"2": "398.00", "1": "368.00"}}, {"year": 2018, "type": {"2": "321.00", "1": "291.00"}}], "23": [{"year": 2020, "type": {"2": "401.00", "1": "367.00"}}, {"year": 2019, "type": {"2": "412.00", "1": "380.00"}}, {"year": 2018, "type": {"2": "380.00", "1": "354.00"}}], "32": [{"year": 2020, "type": {"1": "320.00", "2": "300.00"}}, {"year": 2019, "type": {"1": "313.00", "2": "295.00"}}, {"year": 2018, "type": {"2": "293.00", "1": "292.00"}}], "33": [{"year": 2020, "type": {"3": "495.00"}}, {"year": 2019, "type": {"3": "517.00"}}, {"year": 2018, "type": {"3": "504.00"}}], "34": [{"year": 2020, "type": {"2": "505.00", "1": "457.00"}}, {"year": 2019, "type": {"2": "512.00", "1": "441.00"}}, {"year": 2018, "type": {"2": "494.00", "1": "444.00"}}], "35": [{"year": 2020, "type": {"1": "402.00"}}, {"year": 2019, "type": {"2": "467.00", "1": "393.00"}}, {"year": 2018, "type": {"2": "432.00", "1": "375.00"}}], "36": [{"year": 2020, "type": {"2": "498.00", "1": "467.00"}}, {"year": 2019, "type": {"2": "508.00", "1": "455.00"}}, {"year": 2018, "type": {"2": "500.00", "1": "447.00"}}], "37": [{"year": 2020, "type": {"3": "456.00"}}, {"year": 2019, "type": {"2": "508.00", "1": "452.00"}}, {"year": 2018, "type": {"2": "505.00", "1": "440.00"}}], "41": [{"year": 2020, "type": {"2": "470.00", "1": "439.00"}}, {"year": 2019, "type": {"2": "453.00", "1": "405.00"}}, {"year": 2018, "type": {"2": "441.00", "1": "386.00"}}], "42": [{"year": 2020, "type": {"2": "429.00", "1": "405.00"}}, {"year": 2019, "type": {"2": "446.00", "1": "396.00"}}, {"year": 2018, "type": {"2": "444.00", "1": "381.00"}}], "43": [{"year": 2020, "type": {"2": "526.00", "1": "468.00"}}, {"year": 2019, "type": {"2": "523.00", "1": "449.00"}}, {"year": 2018, "type": {"2": "526.00", "1": "450.00"}}], "44": [{"year": 2020, "type": {"2": "461.00", "1": "439.00"}}, {"year": 2019, "type": {"2": "478.00", "1": "405.00"}}, {"year": 2018, "type": {"2": "451.00", "1": "377.00"}}], "45": [{"year": 2020, "type": {"1": "363.00"}}, {"year": 2019, "type": {"1": "353.00"}}, {"year": 2018, "type": {"1": "352.00"}}], "46": [{"year": 2020, "type": {"3": "481.00"}}, {"year": 2019, "type": {"2": "539.00", "1": "502.00"}}, {"year": 2018, "type": {"2": "513.00", "1": "495.00"}}], "50": [{"year": 2020, "type": {"2": "514.00", "1": "416.00"}}, {"year": 2019, "type": {"2": "477.00", "1": "439.00"}}, {"year": 2018, "type": {"2": "441.00", "1": "428.00"}}], "51": [{"year": 2020, "type": {"2": "462.00", "1": "450.00"}}, {"year": 2019, "type": {"2": "477.00", "1": "465.00"}}, {"year": 2018, "type": {"2": "497.00", "1": "464.00"}}], "52": [{"year": 2020, "type": {"2": "465.00", "1": "388.00"}}, {"year": 2019, "type": {"2": "453.00", "1": "372.00"}}, {"year": 2018, "type": {"2": "479.00", "1": "379.00"}}], "53": [{"year": 2020, "type": {"2": "481.00", "1": "448.00"}}, {"year": 2019, "type": {"2": "465.00", "1": "414.00"}}, {"year": 2018, "type": {"2": "470.00", "1": "396.00"}}], "61": [{"year": 2020, "type": {"2": "429.00", "1": "381.00"}}, {"year": 2019, "type": {"2": "412.00", "1": "391.00"}}, {"year": 2018, "type": {"2": "368.00", "1": "345.00"}}], "62": [{"year": 2020, "type": {"2": "443.00", "1": "372.00"}}, {"year": 2019, "type": {"2": "418.00", "1": "381.00"}}, {"year": 2018, "type": {"1": "369.00", "2": "366.00"}}], "63": [{"year": 2020, "type": {"2": "412.00", "1": "333.00"}}, {"year": 2019, "type": {"2": "407.00", "1": "348.00"}}, {"year": 2018, "type": {"2": "380.00", "1": "334.00"}}], "64": [{"year": 2020, "type": {"2": "473.00", "1": "379.00"}}, {"year": 2019, "type": {"2": "472.00", "1": "388.00"}}, {"year": 2018, "type": {"2": "448.00", "1": "377.00"}}], "65": [{"year": 2020, "type": {"2": "372.00", "1": "323.00"}}, {"year": 2019, "type": {"2": "387.00", "1": "343.00"}}, {"year": 2018, "type": {"2": "375.00", "1": "349.00"}}]}, "pro_type": {"12": ["3", "2", "1"], "13": ["2", "1"], "14": ["2", "1"], "15": ["2", "1"], "21": ["2", "1"], "22": ["2", "1"], "23": ["2", "1"], "32": ["1", "2"], "33": ["3"], "34": ["2", "1"], "35": ["1", "2"], "36": ["2", "1"], "37": ["3", "2", "1"], "41": ["2", "1"], "42": ["2", "1"], "43": ["2", "1"], "44": ["2", "1"], "45": ["1"], "46": ["3", "2", "1"], "50": ["2", "1"], "51": ["2", "1"], "52": ["2", "1"], "53": ["2", "1"], "61": ["2", "1"], "62": ["2", "1"], "63": ["2", "1"], "64": ["2", "1"], "65": ["2", "1"]}, "province_score_year": "2020", "qs_world": "0", "fenxiao": []}