{"school_id": "3218", "data_code": "457600302", "name": "\u5e7f\u897f\u91d1\u878d\u804c\u4e1a\u6280\u672f\u5b66\u9662", "type": "5006", "school_type": "6001", "school_nature": "36000", "level": "2002", "code_enroll": "1451200", "belong": "\u5e7f\u897f\u58ee\u65cf\u81ea\u6cbb\u533a", "f985": "2", "f211": "2", "department": "2", "admissions": "2", "central": "2", "dual_class": "38003", "is_seal": "1", "num_subject": "0", "num_master": "0", "num_doctor": "0", "num_academician": "0", "num_library": "0", "num_lab": "0", "province_id": "45", "city_id": "4501", "county_id": "0", "is_ads": "1", "is_recruitment": "1", "create_date": "2014", "area": 532, "old_name": "", "status": "1", "add_id": "0", "add_time": "2018-12-08 17:23:25", "update_id": "0", "update_time": "2021-03-18 11:11:11", "ad_level": "3", "short": "\u5e7f\u897f\u91d1\u878d\u804c\u9662", "e_pc": "1", "e_app": "1", "ruanke_rank": "0", "single": "75001", "colleges_level": "", "doublehigh": "0", "wsl_rank": "0", "qs_rank": "0", "xyh_rank": "0", "is_sell": "1", "eol_rank": "2168", "school_batch": "10,158", "us_rank": "0", "is_logo": "1", "num_master2": "0", "num_doctor2": "0", "ai_status": "1", "logo": "/app/html/upload/logo/3218.jpg", "level_name": "\u4e13\u79d1\uff08\u9ad8\u804c\uff09", "type_name": "\u8d22\u7ecf\u7c7b", "school_type_name": "\u4e13\u79d1\uff08\u9ad8\u804c\uff09", "school_nature_name": "\u516c\u529e", "dual_class_name": "", "xueke_rank": {}, "single_province": "45", "remark": [], "province_name": "\u5e7f\u897f", "city_name": "\u5357\u5b81\u5e02", "town_name": "", "weiwangzhan": "", "urllinks": {"71006": {"school_id": "3218", "link": "https://v1.cnzz.com/z_stat.php?id=1279228532&web_id=1279228532", "type": "71006", "img_url": "", "title": ""}, "71009": {"school_id": "3218", "link": "http://www.gxjrxy.com/", "type": "71009", "img_url": "", "title": ""}, "71008": {"school_id": "3218", "link": "http://www.gxjrxy.com/", "type": "71008", "img_url": "", "title": ""}, "71007": {"school_id": "3218", "link": "http://www.gxeea.cn/", "type": "71007", "img_url": "", "title": ""}, "71005": {"school_id": "3218", "link": "https://answer.eol.cn/fillmess/index?id=3583&source=zsgk_app", "type": "71005", "img_url": "", "title": ""}}, "yjszs": "", "xiaoyuan": "", "email": "gxjzyjj@163.com", "school_email": "", "address": "\u5e7f\u897f\u5357\u5b81\u5e02\u5927\u5b66\u4e1c\u8def91\u53f7", "postcode": "530007", "site": "http://www.gxjrxy.com/zsw/", "school_site": "http://www.gxjrxy.com", "phone": "0771-3245020,0771-3240330", "school_phone": "", "content": "\u5e7f\u897f\u91d1\u878d\u804c\u4e1a\u6280\u672f\u5b66\u9662\uff0c\u4ee5\u4e2d\u56fd\u4eba\u6c11\u94f6\u884c\u603b\u884c\u4e8e1952\u5e74\u521b\u529e\u7684\u5e7f\u897f\u94f6\u884c\u5b66\u6821\u548c1953\u5e74\u8bbe\u7acb\u7684\u5e7f\u897f\u94f6\u884c\u5e72\u90e8\u5b66\u6821\u4e3a\u57fa\u7840\uff0c\u4e8e2014\u5e741\u6708\u7ecf\u5e7f\u897f\u58ee\u65cf\u81ea\u6cbb\u533a\u4eba\u6c11\u653f\u5e9c\u6279\u51c6\u5e76\u62a5\u4e2d\u534e\u4eba\u6c11\u5171\u548c\u56fd\u6559\u80b2\u90e8\u5907\u6848\u800c\u521b\u5efa\uff0c\u76f4\u5c5e\u5e7f\u897f\u58ee\u65cf\u81ea\u6cbb\u533a\u6559\u80b2\u5385\u7ba1\u7406\uff0c\u662f\u5e7f\u897f\u552f\u4e00\u7684\u4e00\u6240\u4ee5\u57f9\u517b\u3001\u57f9\u8bad\u94f6\u884c\u3001\u8bc1\u5238\u3001\u4fdd\u9669\u3001\u4fe1\u8d37\u7b49\u91d1\u878d\u7ecf\u6d4e\u7c7b\u4eba\u624d\u4e3a\u4efb\u52a1\u7684\u5168\u65e5\u5236\u9ad8\u7b49\u804c\u4e1a\u6559\u80b2\u5b66\u5e9c\uff0c\u4eab\u6709\u201c\u5e7f\u897f\u91d1\u878d\u4eba\u624d\u7684\u6447\u7bee\u201d\u4e4b\u7f8e", "video": {"school_id": "3218", "url": "5285890802616508462", "url_type": "2", "img_url": "https://static-data.eol.cn//upload/svideo/1590156071_9128_thumb.jpg"}, "video_pc": {"school_id": "3218", "url": "5285890802616508462", "url_type": "2", "img_url": "https://static-data.eol.cn//upload/svideo/1590156071_9128_thumb.jpg"}, "is_video": 1, "dualclass": [], "special": [{"id": "204149", "school_id": "3218", "special_id": "869", "nation_feature": "2", "province_feature": "2", "is_important": "2", "limit_year": "\u4e09\u5e74", "year": "2019", "level3_weight": "0", "is_video": 2, "special_name": "\u56fd\u9645\u7ecf\u6d4e\u4e0e\u8d38\u6613", "level_name": "\u4e13\u79d1"}, {"id": "88204", "school_id": "3218", "special_id": "900", "nation_feature": "2", "province_feature": "2", "is_important": "2", "limit_year": "\u4e09\u5e74", "year": "2019", "level3_weight": "0", "is_video": 2, "special_name": "\u9152\u5e97\u7ba1\u7406", "level_name": "\u4e13\u79d1"}, {"id": "88205", "school_id": "3218", "special_id": "896", "nation_feature": "2", "province_feature": "2", "is_important": "2", "limit_year": "\u4e09\u5e74", "year": "2019", "level3_weight": "0", "is_video": 2, "special_name": "\u65c5\u6e38\u7ba1\u7406", "level_name": "\u4e13\u79d1"}, {"id": "88201", "school_id": "3218", "special_id": "876", "nation_feature": "2", "province_feature": "2", "is_important": "2", "limit_year": "\u4e09\u5e74", "year": "2019", "level3_weight": "0", "is_video": 2, "special_name": "\u5de5\u5546\u4f01\u4e1a\u7ba1\u7406", "level_name": "\u4e13\u79d1"}, {"id": "88206", "school_id": "3218", "special_id": "882", "nation_feature": "2", "province_feature": "2", "is_important": "2", "limit_year": "\u4e09\u5e74", "year": "2019", "level3_weight": "0", "is_video": 2, "special_name": "\u5e02\u573a\u8425\u9500", "level_name": "\u4e13\u79d1"}, {"id": "88207", "school_id": "3218", "special_id": "886", "nation_feature": "2", "province_feature": "2", "is_important": "2", "limit_year": "\u4e09\u5e74", "year": "2019", "level3_weight": "0", "is_video": 2, "special_name": "\u7535\u5b50\u5546\u52a1", "level_name": "\u4e13\u79d1"}, {"id": "88208", "school_id": "3218", "special_id": "855", "nation_feature": "2", "province_feature": "2", "is_important": "2", "limit_year": "\u4e09\u5e74", "year": "2019", "level3_weight": "0", "is_video": 2, "special_name": "\u8bc1\u5238\u4e0e\u671f\u8d27", "level_name": "\u4e13\u79d1"}, {"id": "88209", "school_id": "3218", "special_id": "858", "nation_feature": "2", "province_feature": "2", "is_important": "2", "limit_year": "\u4e09\u5e74", "year": "2019", "level3_weight": "0", "is_video": 2, "special_name": "\u6295\u8d44\u4e0e\u7406\u8d22", "level_name": "\u4e13\u79d1"}, {"id": "88210", "school_id": "3218", "special_id": "862", "nation_feature": "2", "province_feature": "2", "is_important": "2", "limit_year": "\u4e09\u5e74", "year": "2019", "level3_weight": "0", "is_video": 2, "special_name": "\u8d22\u52a1\u7ba1\u7406", "level_name": "\u4e13\u79d1"}, {"id": "88214", "school_id": "3218", "special_id": "864", "nation_feature": "2", "province_feature": "2", "is_important": "2", "limit_year": "\u4e09\u5e74", "year": "2019", "level3_weight": "0", "is_video": 2, "special_name": "\u5ba1\u8ba1", "level_name": "\u4e13\u79d1"}], "nature_name": "\u516c\u529e", "province_score_min": {"14": {"school_id": "3218", "province_id": "14", "type": "2", "min": "130.00", "year": "2020"}, "21": {"school_id": "3218", "province_id": "21", "type": "2", "min": "429.00", "year": "2020"}, "22": {"school_id": "3218", "province_id": "22", "type": "2", "min": "266.00", "year": "2020"}, "23": {"school_id": "3218", "province_id": "23", "type": "1", "min": "266.00", "year": "2020"}, "36": {"school_id": "3218", "province_id": "36", "type": "2", "min": "150.00", "year": "2020"}, "43": {"school_id": "3218", "province_id": "43", "type": "2", "min": "364.00", "year": "2020"}, "44": {"school_id": "3218", "province_id": "44", "type": "1", "min": "268.00", "year": "2020"}, "45": {"school_id": "3218", "province_id": "45", "type": "2", "min": "262.00", "year": "2020"}, "51": {"school_id": "3218", "province_id": "51", "type": "2", "min": "150.00", "year": "2020"}, "52": {"school_id": "3218", "province_id": "52", "type": "2", "min": "288.00", "year": "2020"}, "53": {"school_id": "3218", "province_id": "53", "type": "2", "min": "399.00", "year": "2020"}, "63": {"school_id": "3218", "province_id": "63", "type": "1", "min": "241.00", "year": "2020"}, "64": {"school_id": "3218", "province_id": "64", "type": "1", "min": "284.00", "year": "2020"}, "15": {"school_id": "3218", "province_id": "15", "type": "1", "min": "298.00", "year": "2019"}, "34": {"school_id": "3218", "province_id": "34", "type": "2", "min": "255.00", "year": "2019"}, "62": {"school_id": "3218", "province_id": "62", "type": "2", "min": "160.00", "year": "2019"}}, "pro_type_min": {"14": [{"year": 2020, "type": {"2": "130.00", "1": "130.00"}}, {"year": 2019, "type": {"2": "130.00", "1": "130.00"}}], "21": [{"year": 2020, "type": {"2": "429.00", "1": "336.00"}}, {"year": 2019, "type": {"2": "368.00", "1": "326.00"}}], "22": [{"year": 2020, "type": {"2": "266.00", "1": "242.00"}}, {"year": 2019, "type": {"2": "304.00", "1": "234.00"}}], "23": [{"year": 2020, "type": {"1": "266.00", "2": "216.00"}}, {"year": 2019, "type": {"1": "219.00", "2": "216.00"}}], "36": [{"year": 2020, "type": {"2": "150.00", "1": "150.00"}}, {"year": 2019, "type": {"2": "160.00", "1": "160.00"}}], "43": [{"year": 2020, "type": {"2": "364.00", "1": "246.00"}}, {"year": 2019, "type": {"2": "332.00", "1": "200.00"}}, {"year": 2018, "type": {"2": "271.00", "1": "200.00"}}], "44": [{"year": 2020, "type": {"1": "268.00"}}], "45": [{"year": 2020, "type": {"2": "262.00", "1": "226.00"}}, {"year": 2019, "type": {"2": "269.00", "1": "238.00"}}, {"year": 2018, "type": {"1": "200.00", "2": "200.00"}}], "51": [{"year": 2020, "type": {"2": "150.00", "1": "150.00"}}, {"year": 2019, "type": {"1": "150.00", "2": "150.00"}}, {"year": 2018, "type": {"1": "340.00", "2": "241.00"}}], "52": [{"year": 2020, "type": {"2": "288.00", "1": "231.00"}}, {"year": 2019, "type": {"2": "379.00", "1": "219.00"}}, {"year": 2018, "type": {"2": "301.00", "1": "218.00"}}], "53": [{"year": 2020, "type": {"2": "399.00", "1": "290.00"}}, {"year": 2019, "type": {"2": "386.00", "1": "284.00"}}, {"year": 2018, "type": {"2": "396.00", "1": "311.00"}}], "63": [{"year": 2020, "type": {"1": "241.00"}}, {"year": 2019, "type": {"1": "254.00"}}], "64": [{"year": 2020, "type": {"1": "284.00"}}], "15": [{"year": 2019, "type": {"1": "298.00", "2": "219.00"}}], "34": [{"year": 2019, "type": {"2": "255.00"}}], "62": [{"year": 2019, "type": {"2": "160.00", "1": "160.00"}}]}, "pro_type": {"14": ["2", "1"], "21": ["2", "1"], "22": ["2", "1"], "23": ["1", "2"], "36": ["2", "1"], "43": ["2", "1"], "44": ["1"], "45": ["2", "1"], "51": ["2", "1"], "52": ["2", "1"], "53": ["2", "1"], "63": ["1"], "64": ["1"], "15": ["1", "2"], "34": ["2"], "62": ["2", "1"]}, "province_score_year": "2020", "qs_world": "0", "fenxiao": []}